[
    {
        "key": "dbln",
        "value": "%7B%2261556196058001%22%3A%22m9ajuiKk%22%2C%22100080682514874%22%3A%22SvLCtD8M%22%2C%22100044797791216%22%3A%22laVg80CL%22%2C%2261558831411809%22%3A%22OciF6fT8%22%7D",
        "domain": "facebook.com",
        "path": "/login/device-based/",
        "hostOnly": false,
        "creation": "2024-09-11T03:03:13.034Z",
        "lastAccessed": "2024-09-11T03:03:13.034Z"
    },
    {
        "key": "datr",
        "value": "tnXJZkvtXSy6KiVnRF1IF36W",
        "domain": "facebook.com",
        "path": "/",
        "hostOnly": false,
        "creation": "2024-09-11T03:03:13.034Z",
        "lastAccessed": "2024-09-11T03:03:13.034Z"
    },
    {
        "key": "sb",
        "value": "tnXJZppGuAoSUQF9O28GudH4",
        "domain": "facebook.com",
        "path": "/",
        "hostOnly": false,
        "creation": "2024-09-11T03:03:13.034Z",
        "lastAccessed": "2024-09-11T03:03:13.034Z"
    },
    {
        "key": "ps_l",
        "value": "1",
        "domain": "facebook.com",
        "path": "/",
        "hostOnly": false,
        "creation": "2024-09-11T03:03:13.034Z",
        "lastAccessed": "2024-09-11T03:03:13.034Z"
    },
    {
        "key": "ps_n",
        "value": "1",
        "domain": "facebook.com",
        "path": "/",
        "hostOnly": false,
        "creation": "2024-09-11T03:03:13.034Z",
        "lastAccessed": "2024-09-11T03:03:13.034Z"
    },
    {
        "key": "dpr",
        "value": "2.549999952316284",
        "domain": "facebook.com",
        "path": "/",
        "hostOnly": false,
        "creation": "2024-09-11T03:03:13.034Z",
        "lastAccessed": "2024-09-11T03:03:13.034Z"
    },
    {
        "key": "vpd",
        "value": "v1%3B786x424x2.549999952316284",
        "domain": "facebook.com",
        "path": "/",
        "hostOnly": false,
        "creation": "2024-09-11T03:03:13.034Z",
        "lastAccessed": "2024-09-11T03:03:13.034Z"
    },
    {
        "key": "locale",
        "value": "en_GB",
        "domain": "facebook.com",
        "path": "/",
        "hostOnly": false,
        "creation": "2024-09-11T03:03:13.034Z",
        "lastAccessed": "2024-09-11T03:03:13.034Z"
    },
    {
        "key": "c_user",
        "value": "61564599938847",
        "domain": "facebook.com",
        "path": "/",
        "hostOnly": false,
        "creation": "2024-09-11T03:03:13.034Z",
        "lastAccessed": "2024-09-11T03:03:13.034Z"
    },
    {
        "key": "fr",
        "value": "0k3Wj7VWQI4erDcuu.AWWZsnCG9OFY23Q4TTJXveEx_Rw.BmyXW2..AAA.0.0.Bm4FZC.AWXDLTVvp0c",
        "domain": "facebook.com",
        "path": "/",
        "hostOnly": false,
        "creation": "2024-09-11T03:03:13.034Z",
        "lastAccessed": "2024-09-11T03:03:13.034Z"
    },
    {
        "key": "xs",
        "value": "27%3A2cLDef7Ks3xujg%3A2%3A1725978178%3A-1%3A1904",
        "domain": "facebook.com",
        "path": "/",
        "hostOnly": false,
        "creation": "2024-09-11T03:03:13.034Z",
        "lastAccessed": "2024-09-11T03:03:13.034Z"
    },
    {
        "key": "m_page_voice",
        "value": "61564599938847",
        "domain": "facebook.com",
        "path": "/",
        "hostOnly": false,
        "creation": "2024-09-11T03:03:13.034Z",
        "lastAccessed": "2024-09-11T03:03:13.034Z"
    },
    {
        "key": "wd",
        "value": "424x786",
        "domain": "facebook.com",
        "path": "/",
        "hostOnly": false,
        "creation": "2024-09-11T03:03:13.034Z",
        "lastAccessed": "2024-09-11T03:03:13.034Z"
    },
    {
        "key": "fbl_st",
        "value": "100432588%3BT%3A28767063",
        "domain": "facebook.com",
        "path": "/",
        "hostOnly": false,
        "creation": "2024-09-11T03:03:13.034Z",
        "lastAccessed": "2024-09-11T03:03:13.034Z"
    },
    {
        "key": "wl_cbv",
        "value": "v2%3Bclient_version%3A2617%3Btimestamp%3A1726023780",
        "domain": "facebook.com",
        "path": "/",
        "hostOnly": false,
        "creation": "2024-09-11T03:03:13.034Z",
        "lastAccessed": "2024-09-11T03:03:13.034Z"
    }
]
